ghtrack
