Metadata-Version: 2.1
Name: GhTrack
Version: 1.0.1
Summary: An Python module api app
Home-page: https://github.com/zinaLacina/github-track
Author: Lacina ZINA
Author-email: zinalacina@yahoo.com
License: UNKNOWN
Project-URL: Bug Tracker, https://github.com/zinaLacina/github-track/issues
Platform: UNKNOWN
Classifier: Development Status :: 4 - Beta
Classifier: Intended Audience :: Developers
Classifier: License :: OSI Approved :: The Unlicense (Unlicense)
Classifier: Programming Language :: Python :: 3 :: Only
Classifier: Programming Language :: Python :: 3.6
Classifier: Programming Language :: Python :: 3.7
Classifier: Programming Language :: Python :: 3.8
Classifier: Topic :: Utilities
Classifier: Typing :: Typed
Requires-Python: >=3.6
License-File: LICENCE.txt
